README.md
setup.py
docker_interface/__init__.py
docker_interface/cli.py
docker_interface/docker_interface.py
docker_interface/util.py
docker_interface.egg-info/PKG-INFO
docker_interface.egg-info/SOURCES.txt
docker_interface.egg-info/dependency_links.txt
docker_interface.egg-info/entry_points.txt
docker_interface.egg-info/requires.txt
docker_interface.egg-info/top_level.txt
docker_interface/plugins/__init__.py
docker_interface/plugins/base.py
docker_interface/plugins/build.py
docker_interface/plugins/google.py
docker_interface/plugins/python.py
docker_interface/plugins/run.py
docker_interface/plugins/user.py