Metadata-Version: 1.0
Name: docker-interface
Version: 0.2.8
Summary: Declarative interface for building images and running commands in containers using Docker.
Home-page: https://github.com/spotify/docker_interface
Author: Till Hoffmann
Author-email: till@spotify.com
License: License :: OSI Approved :: Apache Software License
Platform: UNKNOWN
